gold_today/__init__.py
pricesgoldtoday_indonesia-0.0.4.dist-info/licenses/LICENSE
pricesgoldtoday_indonesia-0.0.4.dist-info/METADATA
pricesgoldtoday_indonesia-0.0.4.dist-info/WHEEL
pricesgoldtoday_indonesia-0.0.4.dist-info/top_level.txt
pricesgoldtoday_indonesia-0.0.4.dist-info/RECORD
