Metadata-Version: 2.4
Name: pricesgoldtoday-indonesia
Version: 0.0.4
Summary: This package will get update price gold in Indonesia, source from lakuemas.com
Home-page: https://github.com/masalee-dev/price-gold-today-id
Author: Haeder Ali
Author-email: Haeder Ali <haederalee@gmail.com>
License-Expression: GPL-3.0-only WITH Classpath-exception-2.0 OR BSD-3-Clause
Project-URL: Homepage, https://github.com/Masalee-hub
Project-URL: Issues, https://github.com/orgs/masalee-dev/repositories
Classifier: Programming Language :: Python :: 3
Classifier: Operating System :: OS Independent
Requires-Python: >=3.13
License-File: LICENSE
Dynamic: author
Dynamic: home-page
Dynamic: license-file
Dynamic: requires-python
